<?xml version="1.0" encoding="UTF-8"?>
<beans xmlns="http://www.springframework.org/schema/beans"
       xmlns:xsi="http://www.w3.org/2001/XMLSchema-instance"
       xsi:schemaLocation="http://www.springframework.org/schema/beans http://www.springframework.org/schema/beans/spring-beans.xsd">

    <!--  基本方式  -->
<!--    <bean id="textEditor" class="com.test.autoWiring.TextEditor">-->
<!--        <property name="name" value="Generic Text Editor"></property>-->
<!--        <property name="spellChecker" ref="spellChecker"></property>-->
<!--    </bean>-->

<!--  自动装配模式’byName’  -->
<!--    <bean id="textEditor" class="com.test.autoWiring.TextEditor" autowire="byName">-->
<!--        <property name="name" value="Generic Text Editor"></property>-->
<!--    </bean>-->

<!--  自动装配模式’byType’  -->
<!--    <bean id="textEditor" class="com.test.autoWiring.TextEditor" autowire="byType">-->
<!--        <property name="name" value="Generic Text Editor"></property>-->
<!--    </bean>-->

    <bean id="textEditor" class="com.test.autoWiring.TextEditor" autowire="byType">
        <property name="name" value="Generic Text Editor"></property>
    </bean>

    <bean id="spellChecker" class="com.test.autoWiring.SpellChecker"></bean>
</beans>